auto_setup/__init__.py
auto_setup/main.py
auto_setup-0.1.1.dist-info/METADATA
auto_setup-0.1.1.dist-info/WHEEL
auto_setup-0.1.1.dist-info/entry_points.txt
auto_setup-0.1.1.dist-info/top_level.txt
auto_setup-0.1.1.dist-info/RECORD
